json_validation_al/__init__.py
json_validation_al/base.py
json_validation_al/implementations/__init__.py
json_validation_al/implementations/event_validation_main.py
json_validation_al-0.0.9.dist-info/METADATA
json_validation_al-0.0.9.dist-info/WHEEL
json_validation_al-0.0.9.dist-info/licenses/LICENSE.txt
json_validation_al-0.0.9.dist-info/RECORD
