Metadata-Version: 2.3
Name: json_validation_al
Version: 0.0.9
Summary: A wrapper package for the jsonschema library to validate JSON data against a schema.
Author-email: Tiaan Nieuwoudt <tiaan@al.co.za>
Maintainer-email: Tiaan Nieuwoudt <tiaan@al.co.za>
License: Copyright (c) 2016 The Python Packaging Authority (PyPA)
License-File: LICENSE.txt
Keywords: json,jsonschema,schema,validate,validation
Classifier: Development Status :: 3 - Alpha
Classifier: Intended Audience :: Developers
Classifier: License :: OSI Approved :: MIT License
Classifier: Programming Language :: Python :: 3
Classifier: Programming Language :: Python :: 3.8
Classifier: Programming Language :: Python :: 3.9
Classifier: Programming Language :: Python :: 3.10
Classifier: Programming Language :: Python :: 3.11
Classifier: Programming Language :: Python :: 3.12
Classifier: Topic :: Software Development :: Libraries :: Python Modules
Requires-Python: >=3.8
Requires-Dist: jsonschema==4.23.0
